<?xml version="1.0" encoding="utf-8" ?>

<cls:class
	name="Writer"
	type="http://metalx.org/Writer"
	xmlns="http://metalx.org/Program"
	xmlns:dbg="http://metalx.org/i386/Functions/Debug"
	xmlns:lst="http://metalx.org/i386/Functions/List"
	xmlns:con="http://metalx.org/i386/Functions/Console"
	xmlns:int="http://metalx.org/i386/Functions/Integer"
	xmlns:str="http://metalx.org/i386/Functions/String"
	xmlns:clsf="http://metalx.org/i386/Functions/Class"
	xmlns:var="http://metalx.org/Variable"
	xmlns:sys="http://metalx.org/i386/Functions/System"
	xmlns:cat="http://metalx.org/i386/Functions/Catalog"
	xmlns:obj="http://metalx.org/i386/Functions/Object"
	xmlns:asc="http://metalx.org/Ansi/Ascii"
	xmlns:logic="http://metalx.org/Intel/80386/Logic"
	xmlns:math="http://metalx.org/Intel/80386/Math"
	xmlns:imm="http://metalx.org/Intel/80386/Immediate"
	xmlns:inc="http://metalx.org/Intel/80386/Increment"
	xmlns:cpu="http://metalx.org/Intel/80386/Operators"
	xmlns:op="http://metalx.org/Intel/80386/Operands"
	xmlns:cls="http://metalx.org/Class">

	<cls:method name="WriteObject" type="http://metalx.org/Writer">
		<cls:parameter name="Object" type="http://metalx.org/Object"/>

		<cpu:ReturnToNearCaller/>
	</cls:method>

	<cls:method name="WriteBytes" type="http://metalx.org/Writer">
		<cls:parameter name="Value" type="http://metalx.org/String"/>

		<cpu:ReturnToNearCaller/>
	</cls:method>

	<cls:method name="WriteBoolean" type="http://metalx.org/Writer">
		<cls:parameter name="Value" type="http://metalx.org/String"/>

		<cpu:ReturnToNearCaller/>
	</cls:method>

	<cls:method name="WriteByte" type="http://metalx.org/Writer">
		<cls:parameter name="Value" type="http://metalx.org/String"/>

		<cpu:ReturnToNearCaller/>
	</cls:method>

	<cls:method name="WriteShort" type="http://metalx.org/Writer">
		<cls:parameter name="Value" type="http://metalx.org/String"/>

		<cpu:ReturnToNearCaller/>
	</cls:method>

	<cls:method name="WriteInteger" type="http://metalx.org/Writer">
		<cls:parameter name="Value" type="http://metalx.org/String"/>

		<cpu:ReturnToNearCaller/>
	</cls:method>

	<cls:method name="WriteFloat" type="http://metalx.org/Writer">
		<cls:parameter name="Value" type="http://metalx.org/String"/>

		<cpu:ReturnToNearCaller/>
	</cls:method>

	<cls:method name="WriteDouble" type="http://metalx.org/Writer">
		<cls:parameter name="Value" type="http://metalx.org/String"/>

		<cpu:ReturnToNearCaller/>
	</cls:method>

	<cls:method name="WriteReal" type="http://metalx.org/Writer">
		<cls:parameter name="Value" type="http://metalx.org/String"/>

		<cpu:ReturnToNearCaller/>
	</cls:method>

	<cls:method name="WriteString" type="http://metalx.org/Writer">
		<cls:parameter name="Value" type="http://metalx.org/String"/>

		<cpu:ReturnToNearCaller/>
	</cls:method>

	<cls:method name="Flush" type="http://metalx.org/Writer">
		<cpu:ReturnToNearCaller/>
	</cls:method>

	<cls:method name="ToString" type="http://metalx.org/String">
		<cpu:CopyImmediateToDI/>
		<addressOf ref="className" type="Absolute32"/>

		<str:CreateObject/>

		<cpu:ReturnToNearCaller/>

		<var:string id="className">Writer</var:string>
	</cls:method>

	<cls:method name="GetClass" type="http://metalx.org/Class">
		<cpu:CopyRegisterToOperand/>
		<op:DI-SIRegister/>

		<obj:GetType/>

		<cpu:CopyRegisterToOperand/>
		<op:SI-DIRegister/>

		<clsf:CreateObject/>

		<cpu:ReturnToNearCaller/>
	</cls:method>

	<cls:method name="GetClass" type="http://metalx.org/Class" static="true">
		<cpu:CopyRegisterToOperand/>
		<op:BX-DIRegister/>

		<clsf:CreateObject/>

		<cpu:ReturnToNearCaller/>
	</cls:method>
</cls:class>