<?xml version="1.0" encoding="utf-8" ?>

<platform xmlns="http://metalx.org/Platform" namespace="http://metalx.org/Commodore64/Color">
	<constants>
		<constant name="Black" value="00"/>
		<constant name="White" value="01"/>
		<constant name="Red" value="02"/>
		<constant name="Cyan" value="03"/>
		<constant name="Violet" value="04"/>
		<constant name="Green" value="05"/>
		<constant name="Blue" value="06"/>
		<constant name="Yellow" value="07"/>
		<constant name="Orange" value="08"/>
		<constant name="Brown" value="09"/>
		<constant name="LightRed" value="0a"/>
		<constant name="DarkGray" value="0b"/>
		<constant name="Gray" value="0c"/>
		<constant name="LightGreen" value="0d"/>
		<constant name="LightBlue" value="0e"/>
		<constant name="LightGray" value="0f"/>
	</constants>
</platform>