<?xml version="1.0" encoding="utf-8" ?>
<platform xmlns="http://metalx.org/Platform" namespace="http://metalx.org/Intel/80286/Operands">
	<constants>
		<constant name="AL-BXPlusSIAddress" value="00"/>
		<constant name="AL-BXPlusDIAddress" value="01"/>
		<constant name="AL-BPPlusSIAddress" value="02"/>
		<constant name="AL-BPPlusDIAddress" value="03"/>
		<constant name="AL-SIAddress" value="04"/>
		<constant name="AL-DIAddress" value="05"/>
		<constant name="AL-ImmediateAddress" value="06"/>
		<constant name="AL-BXAddress" value="07"/>
		<constant name="AX-BXPlusSIAddress" value="00"/>
		<constant name="AX-BXPlusDIAddress" value="01"/>
		<constant name="AX-BPPlusSIAddress" value="02"/>
		<constant name="AX-BPPlusDIAddress" value="03"/>
		<constant name="AX-SIAddress" value="04"/>
		<constant name="AX-DIAddress" value="05"/>
		<constant name="AX-ImmediateAddress" value="06"/>
		<constant name="AX-BXAddress" value="07"/>
		<constant name="CL-BXPlusSIAddress" value="08"/>
		<constant name="CL-BXPlusDIAddress" value="09"/>
		<constant name="CL-BPPlusSIAddress" value="0A"/>
		<constant name="CL-BPPlusDIAddress" value="0B"/>
		<constant name="CL-SIAddress" value="0C"/>
		<constant name="CL-DIAddress" value="0D"/>
		<constant name="CL-ImmediateAddress" value="0E"/>
		<constant name="CL-BXAddress" value="0F"/>
		<constant name="CX-BXPlusSIAddress" value="08"/>
		<constant name="CX-BXPlusDIAddress" value="09"/>
		<constant name="CX-BPPlusSIAddress" value="0A"/>
		<constant name="CX-BPPlusDIAddress" value="0B"/>
		<constant name="CX-SIAddress" value="0C"/>
		<constant name="CX-DIAddress" value="0D"/>
		<constant name="CX-ImmediateAddress" value="0E"/>
		<constant name="CX-BXAddress" value="0F"/>
		<constant name="DL-BXPlusSIAddress" value="10"/>
		<constant name="DL-BXPlusDIAddress" value="11"/>
		<constant name="DL-BPPlusSIAddress" value="12"/>
		<constant name="DL-BPPlusDIAddress" value="13"/>
		<constant name="DL-SIAddress" value="14"/>
		<constant name="DL-DIAddress" value="15"/>
		<constant name="DL-ImmediateAddress" value="16"/>
		<constant name="DL-BXAddress" value="17"/>
		<constant name="DX-BXPlusSIAddress" value="10"/>
		<constant name="DX-BXPlusDIAddress" value="11"/>
		<constant name="DX-BPPlusSIAddress" value="12"/>
		<constant name="DX-BPPlusDIAddress" value="13"/>
		<constant name="DX-SIAddress" value="14"/>
		<constant name="DX-DIAddress" value="15"/>
		<constant name="DX-ImmediateAddress" value="16"/>
		<constant name="DX-BXAddress" value="17"/>
		<constant name="BL-BXPlusSIAddress" value="18"/>
		<constant name="BL-BXPlusDIAddress" value="19"/>
		<constant name="BL-BPPlusSIAddress" value="1A"/>
		<constant name="BL-BPPlusDIAddress" value="1B"/>
		<constant name="BL-SIAddress" value="1C"/>
		<constant name="BL-DIAddress" value="1D"/>
		<constant name="BL-ImmediateAddress" value="1E"/>
		<constant name="BL-BXAddress" value="1F"/>
		<constant name="BX-BXPlusSIAddress" value="18"/>
		<constant name="BX-BXPlusDIAddress" value="19"/>
		<constant name="BX-BPPlusSIAddress" value="1A"/>
		<constant name="BX-BPPlusDIAddress" value="1B"/>
		<constant name="BX-SIAddress" value="1C"/>
		<constant name="BX-DIAddress" value="1D"/>
		<constant name="BX-ImmediateAddress" value="1E"/>
		<constant name="BX-BXAddress" value="1F"/>
		<constant name="AH-BXPlusSIAddress" value="20"/>
		<constant name="AH-BXPlusDIAddress" value="21"/>
		<constant name="AH-BPPlusSIAddress" value="22"/>
		<constant name="AH-BPPlusDIAddress" value="23"/>
		<constant name="AH-SIAddress" value="24"/>
		<constant name="AH-DIAddress" value="25"/>
		<constant name="AH-ImmediateAddress" value="26"/>
		<constant name="AH-BXAddress" value="27"/>
		<constant name="SP-BXPlusSIAddress" value="20"/>
		<constant name="SP-BXPlusDIAddress" value="21"/>
		<constant name="SP-BPPlusSIAddress" value="22"/>
		<constant name="SP-BPPlusDIAddress" value="23"/>
		<constant name="SP-SIAddress" value="24"/>
		<constant name="SP-DIAddress" value="25"/>
		<constant name="SP-ImmediateAddress" value="26"/>
		<constant name="SP-BXAddress" value="27"/>
		<constant name="CH-BXPlusSIAddress" value="28"/>
		<constant name="CH-BXPlusDIAddress" value="29"/>
		<constant name="CH-BPPlusSIAddress" value="2A"/>
		<constant name="CH-BPPlusDIAddress" value="2B"/>
		<constant name="CH-SIAddress" value="2C"/>
		<constant name="CH-DIAddress" value="2D"/>
		<constant name="CH-ImmediateAddress" value="2E"/>
		<constant name="CH-BXAddress" value="2F"/>
		<constant name="BP-BXPlusSIAddress" value="28"/>
		<constant name="BP-BXPlusDIAddress" value="29"/>
		<constant name="BP-BPPlusSIAddress" value="2A"/>
		<constant name="BP-BPPlusDIAddress" value="2B"/>
		<constant name="BP-SIAddress" value="2C"/>
		<constant name="BP-DIAddress" value="2D"/>
		<constant name="BP-ImmediateAddress" value="2E"/>
		<constant name="BP-BXAddress" value="2F"/>
		<constant name="DH-BXPlusSIAddress" value="30"/>
		<constant name="DH-BXPlusDIAddress" value="31"/>
		<constant name="DH-BPPlusSIAddress" value="32"/>
		<constant name="DH-BPPlusDIAddress" value="33"/>
		<constant name="DH-SIAddress" value="34"/>
		<constant name="DH-DIAddress" value="35"/>
		<constant name="DH-ImmediateAddress" value="36"/>
		<constant name="DH-BXAddress" value="37"/>
		<constant name="SI-BXPlusSIAddress" value="30"/>
		<constant name="SI-BXPlusDIAddress" value="31"/>
		<constant name="SI-BPPlusSIAddress" value="32"/>
		<constant name="SI-BPPlusDIAddress" value="33"/>
		<constant name="SI-SIAddress" value="34"/>
		<constant name="SI-DIAddress" value="35"/>
		<constant name="SI-ImmediateAddress" value="36"/>
		<constant name="SI-BXAddress" value="37"/>
		<constant name="BH-BXPlusSIAddress" value="38"/>
		<constant name="BH-BXPlusDIAddress" value="39"/>
		<constant name="BH-BPPlusSIAddress" value="3A"/>
		<constant name="BH-BPPlusDIAddress" value="3B"/>
		<constant name="BH-SIAddress" value="3C"/>
		<constant name="BH-DIAddress" value="3D"/>
		<constant name="BH-ImmediateAddress" value="3E"/>
		<constant name="BH-BXAddress" value="3F"/>
		<constant name="DI-BXPlusSIAddress" value="38"/>
		<constant name="DI-BXPlusDIAddress" value="39"/>
		<constant name="DI-BPPlusSIAddress" value="3A"/>
		<constant name="DI-BPPlusDIAddress" value="3B"/>
		<constant name="DI-SIAddress" value="3C"/>
		<constant name="DI-DIAddress" value="3D"/>
		<constant name="DI-ImmediateAddress" value="3E"/>
		<constant name="DI-BXAddress" value="3F"/>
		<constant name="AL-BXPlusSIAddressPlusImmediate8" value="40"/>
		<constant name="AL-BXPlusDIAddressPlusImmediate8" value="41"/>
		<constant name="AL-BPPlusSIAddressPlusImmediate8" value="42"/>
		<constant name="AL-BPPlusDIAddressPlusImmediate8" value="43"/>
		<constant name="AL-SIAddressPlusImmediate8" value="44"/>
		<constant name="AL-DIAddressPlusImmediate8" value="45"/>
		<constant name="AL-BPAddressPlusImmediate8" value="46"/>
		<constant name="AL-BXAddressPlusImmediate8" value="47"/>
		<constant name="AX-BXPlusSIAddressPlusImmediate8" value="40"/>
		<constant name="AX-BXPlusDIAddressPlusImmediate8" value="41"/>
		<constant name="AX-BPPlusSIAddressPlusImmediate8" value="42"/>
		<constant name="AX-BPPlusDIAddressPlusImmediate8" value="43"/>
		<constant name="AX-SIAddressPlusImmediate8" value="44"/>
		<constant name="AX-DIAddressPlusImmediate8" value="45"/>
		<constant name="AX-BPAddressPlusImmediate8" value="46"/>
		<constant name="AX-BXAddressPlusImmediate8" value="47"/>
		<constant name="CL-BXPlusSIAddressPlusImmediate8" value="48"/>
		<constant name="CL-BXPlusDIAddressPlusImmediate8" value="49"/>
		<constant name="CL-BPPlusSIAddressPlusImmediate8" value="4A"/>
		<constant name="CL-BPPlusDIAddressPlusImmediate8" value="4B"/>
		<constant name="CL-SIAddressPlusImmediate8" value="4C"/>
		<constant name="CL-DIAddressPlusImmediate8" value="4D"/>
		<constant name="CL-BPAddressPlusImmediate8" value="4E"/>
		<constant name="CL-BXAddressPlusImmediate8" value="4F"/>
		<constant name="CX-BXPlusSIAddressPlusImmediate8" value="48"/>
		<constant name="CX-BXPlusDIAddressPlusImmediate8" value="49"/>
		<constant name="CX-BPPlusSIAddressPlusImmediate8" value="4A"/>
		<constant name="CX-BPPlusDIAddressPlusImmediate8" value="4B"/>
		<constant name="CX-SIAddressPlusImmediate8" value="4C"/>
		<constant name="CX-DIAddressPlusImmediate8" value="4D"/>
		<constant name="CX-BPAddressPlusImmediate8" value="4E"/>
		<constant name="CX-BXAddressPlusImmediate8" value="4F"/>
		<constant name="DL-BXPlusSIAddressPlusImmediate8" value="50"/>
		<constant name="DL-BXPlusDIAddressPlusImmediate8" value="51"/>
		<constant name="DL-BPPlusSIAddressPlusImmediate8" value="52"/>
		<constant name="DL-BPPlusDIAddressPlusImmediate8" value="53"/>
		<constant name="DL-SIAddressPlusImmediate8" value="54"/>
		<constant name="DL-DIAddressPlusImmediate8" value="55"/>
		<constant name="DL-BPAddressPlusImmediate8" value="56"/>
		<constant name="DL-BXAddressPlusImmediate8" value="57"/>
		<constant name="DX-BXPlusSIAddressPlusImmediate8" value="50"/>
		<constant name="DX-BXPlusDIAddressPlusImmediate8" value="51"/>
		<constant name="DX-BPPlusSIAddressPlusImmediate8" value="52"/>
		<constant name="DX-BPPlusDIAddressPlusImmediate8" value="53"/>
		<constant name="DX-SIAddressPlusImmediate8" value="54"/>
		<constant name="DX-DIAddressPlusImmediate8" value="55"/>
		<constant name="DX-BPAddressPlusImmediate8" value="56"/>
		<constant name="DX-BXAddressPlusImmediate8" value="57"/>
		<constant name="BL-BXPlusSIAddressPlusImmediate8" value="58"/>
		<constant name="BL-BXPlusDIAddressPlusImmediate8" value="59"/>
		<constant name="BL-BPPlusSIAddressPlusImmediate8" value="5A"/>
		<constant name="BL-BPPlusDIAddressPlusImmediate8" value="5B"/>
		<constant name="BL-SIAddressPlusImmediate8" value="5C"/>
		<constant name="BL-DIAddressPlusImmediate8" value="5D"/>
		<constant name="BL-BPAddressPlusImmediate8" value="5E"/>
		<constant name="BL-BXAddressPlusImmediate8" value="5F"/>
		<constant name="BX-BXPlusSIAddressPlusImmediate8" value="58"/>
		<constant name="BX-BXPlusDIAddressPlusImmediate8" value="59"/>
		<constant name="BX-BPPlusSIAddressPlusImmediate8" value="5A"/>
		<constant name="BX-BPPlusDIAddressPlusImmediate8" value="5B"/>
		<constant name="BX-SIAddressPlusImmediate8" value="5C"/>
		<constant name="BX-DIAddressPlusImmediate8" value="5D"/>
		<constant name="BX-BPAddressPlusImmediate8" value="5E"/>
		<constant name="BX-BXAddressPlusImmediate8" value="5F"/>
		<constant name="AH-BXPlusSIAddressPlusImmediate8" value="60"/>
		<constant name="AH-BXPlusDIAddressPlusImmediate8" value="61"/>
		<constant name="AH-BPPlusSIAddressPlusImmediate8" value="62"/>
		<constant name="AH-BPPlusDIAddressPlusImmediate8" value="63"/>
		<constant name="AH-SIAddressPlusImmediate8" value="64"/>
		<constant name="AH-DIAddressPlusImmediate8" value="65"/>
		<constant name="AH-BPAddressPlusImmediate8" value="66"/>
		<constant name="AH-BXAddressPlusImmediate8" value="67"/>
		<constant name="SP-BXPlusSIAddressPlusImmediate8" value="60"/>
		<constant name="SP-BXPlusDIAddressPlusImmediate8" value="61"/>
		<constant name="SP-BPPlusSIAddressPlusImmediate8" value="62"/>
		<constant name="SP-BPPlusDIAddressPlusImmediate8" value="63"/>
		<constant name="SP-SIAddressPlusImmediate8" value="64"/>
		<constant name="SP-DIAddressPlusImmediate8" value="65"/>
		<constant name="SP-BPAddressPlusImmediate8" value="66"/>
		<constant name="SP-BXAddressPlusImmediate8" value="67"/>
		<constant name="CH-BXPlusSIAddressPlusImmediate8" value="68"/>
		<constant name="CH-BXPlusDIAddressPlusImmediate8" value="69"/>
		<constant name="CH-BPPlusSIAddressPlusImmediate8" value="6A"/>
		<constant name="CH-BPPlusDIAddressPlusImmediate8" value="6B"/>
		<constant name="CH-SIAddressPlusImmediate8" value="6C"/>
		<constant name="CH-DIAddressPlusImmediate8" value="6D"/>
		<constant name="CH-BPAddressPlusImmediate8" value="6E"/>
		<constant name="CH-BXAddressPlusImmediate8" value="6F"/>
		<constant name="BP-BXPlusSIAddressPlusImmediate8" value="68"/>
		<constant name="BP-BXPlusDIAddressPlusImmediate8" value="69"/>
		<constant name="BP-BPPlusSIAddressPlusImmediate8" value="6A"/>
		<constant name="BP-BPPlusDIAddressPlusImmediate8" value="6B"/>
		<constant name="BP-SIAddressPlusImmediate8" value="6C"/>
		<constant name="BP-DIAddressPlusImmediate8" value="6D"/>
		<constant name="BP-BPAddressPlusImmediate8" value="6E"/>
		<constant name="BP-BXAddressPlusImmediate8" value="6F"/>
		<constant name="DH-BXPlusSIAddressPlusImmediate8" value="70"/>
		<constant name="DH-BXPlusDIAddressPlusImmediate8" value="71"/>
		<constant name="DH-BPPlusSIAddressPlusImmediate8" value="72"/>
		<constant name="DH-BPPlusDIAddressPlusImmediate8" value="73"/>
		<constant name="DH-SIAddressPlusImmediate8" value="74"/>
		<constant name="DH-DIAddressPlusImmediate8" value="75"/>
		<constant name="DH-BPAddressPlusImmediate8" value="76"/>
		<constant name="DH-BXAddressPlusImmediate8" value="77"/>
		<constant name="SI-BXPlusSIAddressPlusImmediate8" value="70"/>
		<constant name="SI-BXPlusDIAddressPlusImmediate8" value="71"/>
		<constant name="SI-BPPlusSIAddressPlusImmediate8" value="72"/>
		<constant name="SI-BPPlusDIAddressPlusImmediate8" value="73"/>
		<constant name="SI-SIAddressPlusImmediate8" value="74"/>
		<constant name="SI-DIAddressPlusImmediate8" value="75"/>
		<constant name="SI-BPAddressPlusImmediate8" value="76"/>
		<constant name="SI-BXAddressPlusImmediate8" value="77"/>
		<constant name="BH-BXPlusSIAddressPlusImmediate8" value="78"/>
		<constant name="BH-BXPlusDIAddressPlusImmediate8" value="79"/>
		<constant name="BH-BPPlusSIAddressPlusImmediate8" value="7A"/>
		<constant name="BH-BPPlusDIAddressPlusImmediate8" value="7B"/>
		<constant name="BH-SIAddressPlusImmediate8" value="7C"/>
		<constant name="BH-DIAddressPlusImmediate8" value="7D"/>
		<constant name="BH-BPAddressPlusImmediate8" value="7E"/>
		<constant name="BH-BXAddressPlusImmediate8" value="7F"/>
		<constant name="DI-BXPlusSIAddressPlusImmediate8" value="78"/>
		<constant name="DI-BXPlusDIAddressPlusImmediate8" value="79"/>
		<constant name="DI-BPPlusSIAddressPlusImmediate8" value="7A"/>
		<constant name="DI-BPPlusDIAddressPlusImmediate8" value="7B"/>
		<constant name="DI-SIAddressPlusImmediate8" value="7C"/>
		<constant name="DI-DIAddressPlusImmediate8" value="7D"/>
		<constant name="DI-BPAddressPlusImmediate8" value="7E"/>
		<constant name="DI-BXAddressPlusImmediate8" value="7F"/>
		<constant name="AL-BXPlusSIAddressPlusImmediate16" value="80"/>
		<constant name="AL-BXPlusDIAddressPlusImmediate16" value="81"/>
		<constant name="AL-BPPlusSIAddressPlusImmediate16" value="82"/>
		<constant name="AL-BPPlusDIAddressPlusImmediate16" value="83"/>
		<constant name="AL-SIAddressPlusImmediate16" value="84"/>
		<constant name="AL-DIAddressPlusImmediate16" value="85"/>
		<constant name="AL-BPAddressPlusImmediate16" value="86"/>
		<constant name="AL-BXAddressPlusImmediate16" value="87"/>
		<constant name="AX-BXPlusSIAddressPlusImmediate16" value="80"/>
		<constant name="AX-BXPlusDIAddressPlusImmediate16" value="81"/>
		<constant name="AX-BPPlusSIAddressPlusImmediate16" value="82"/>
		<constant name="AX-BPPlusDIAddressPlusImmediate16" value="83"/>
		<constant name="AX-SIAddressPlusImmediate16" value="84"/>
		<constant name="AX-DIAddressPlusImmediate16" value="85"/>
		<constant name="AX-BPAddressPlusImmediate16" value="86"/>
		<constant name="AX-BXAddressPlusImmediate16" value="87"/>
		<constant name="CL-BXPlusSIAddressPlusImmediate16" value="88"/>
		<constant name="CL-BXPlusDIAddressPlusImmediate16" value="89"/>
		<constant name="CL-BPPlusSIAddressPlusImmediate16" value="8A"/>
		<constant name="CL-BPPlusDIAddressPlusImmediate16" value="8B"/>
		<constant name="CL-SIAddressPlusImmediate16" value="8C"/>
		<constant name="CL-DIAddressPlusImmediate16" value="8D"/>
		<constant name="CL-BPAddressPlusImmediate16" value="8E"/>
		<constant name="CL-BXAddressPlusImmediate16" value="8F"/>
		<constant name="CX-BXPlusSIAddressPlusImmediate16" value="88"/>
		<constant name="CX-BXPlusDIAddressPlusImmediate16" value="89"/>
		<constant name="CX-BPPlusSIAddressPlusImmediate16" value="8A"/>
		<constant name="CX-BPPlusDIAddressPlusImmediate16" value="8B"/>
		<constant name="CX-SIAddressPlusImmediate16" value="8C"/>
		<constant name="CX-DIAddressPlusImmediate16" value="8D"/>
		<constant name="CX-BPAddressPlusImmediate16" value="8E"/>
		<constant name="CX-BXAddressPlusImmediate16" value="8F"/>
		<constant name="DL-BXPlusSIAddressPlusImmediate16" value="90"/>
		<constant name="DL-BXPlusDIAddressPlusImmediate16" value="91"/>
		<constant name="DL-BPPlusSIAddressPlusImmediate16" value="92"/>
		<constant name="DL-BPPlusDIAddressPlusImmediate16" value="93"/>
		<constant name="DL-SIAddressPlusImmediate16" value="94"/>
		<constant name="DL-DIAddressPlusImmediate16" value="95"/>
		<constant name="DL-BPAddressPlusImmediate16" value="96"/>
		<constant name="DL-BXAddressPlusImmediate16" value="97"/>
		<constant name="DX-BXPlusSIAddressPlusImmediate16" value="90"/>
		<constant name="DX-BXPlusDIAddressPlusImmediate16" value="91"/>
		<constant name="DX-BPPlusSIAddressPlusImmediate16" value="92"/>
		<constant name="DX-BPPlusDIAddressPlusImmediate16" value="93"/>
		<constant name="DX-SIAddressPlusImmediate16" value="94"/>
		<constant name="DX-DIAddressPlusImmediate16" value="95"/>
		<constant name="DX-BPAddressPlusImmediate16" value="96"/>
		<constant name="DX-BXAddressPlusImmediate16" value="97"/>
		<constant name="BL-BXPlusSIAddressPlusImmediate16" value="98"/>
		<constant name="BL-BXPlusDIAddressPlusImmediate16" value="99"/>
		<constant name="BL-BPPlusSIAddressPlusImmediate16" value="9A"/>
		<constant name="BL-BPPlusDIAddressPlusImmediate16" value="9B"/>
		<constant name="BL-SIAddressPlusImmediate16" value="9C"/>
		<constant name="BL-DIAddressPlusImmediate16" value="9D"/>
		<constant name="BL-BPAddressPlusImmediate16" value="9E"/>
		<constant name="BL-BXAddressPlusImmediate16" value="9F"/>
		<constant name="BX-BXPlusSIAddressPlusImmediate16" value="98"/>
		<constant name="BX-BXPlusDIAddressPlusImmediate16" value="99"/>
		<constant name="BX-BPPlusSIAddressPlusImmediate16" value="9A"/>
		<constant name="BX-BPPlusDIAddressPlusImmediate16" value="9B"/>
		<constant name="BX-SIAddressPlusImmediate16" value="9C"/>
		<constant name="BX-DIAddressPlusImmediate16" value="9D"/>
		<constant name="BX-BPAddressPlusImmediate16" value="9E"/>
		<constant name="BX-BXAddressPlusImmediate16" value="9F"/>
		<constant name="AH-BXPlusSIAddressPlusImmediate16" value="A0"/>
		<constant name="AH-BXPlusDIAddressPlusImmediate16" value="A1"/>
		<constant name="AH-BPPlusSIAddressPlusImmediate16" value="A2"/>
		<constant name="AH-BPPlusDIAddressPlusImmediate16" value="A3"/>
		<constant name="AH-SIAddressPlusImmediate16" value="A4"/>
		<constant name="AH-DIAddressPlusImmediate16" value="A5"/>
		<constant name="AH-BPAddressPlusImmediate16" value="A6"/>
		<constant name="AH-BXAddressPlusImmediate16" value="A7"/>
		<constant name="SP-BXPlusSIAddressPlusImmediate16" value="A0"/>
		<constant name="SP-BXPlusDIAddressPlusImmediate16" value="A1"/>
		<constant name="SP-BPPlusSIAddressPlusImmediate16" value="A2"/>
		<constant name="SP-BPPlusDIAddressPlusImmediate16" value="A3"/>
		<constant name="SP-SIAddressPlusImmediate16" value="A4"/>
		<constant name="SP-DIAddressPlusImmediate16" value="A5"/>
		<constant name="SP-BPAddressPlusImmediate16" value="A6"/>
		<constant name="SP-BXAddressPlusImmediate16" value="A7"/>
		<constant name="CH-BXPlusSIAddressPlusImmediate16" value="A8"/>
		<constant name="CH-BXPlusDIAddressPlusImmediate16" value="A9"/>
		<constant name="CH-BPPlusSIAddressPlusImmediate16" value="AA"/>
		<constant name="CH-BPPlusDIAddressPlusImmediate16" value="AB"/>
		<constant name="CH-SIAddressPlusImmediate16" value="AC"/>
		<constant name="CH-DIAddressPlusImmediate16" value="AD"/>
		<constant name="CH-BPAddressPlusImmediate16" value="AE"/>
		<constant name="CH-BXAddressPlusImmediate16" value="AF"/>
		<constant name="BP-BXPlusSIAddressPlusImmediate16" value="A8"/>
		<constant name="BP-BXPlusDIAddressPlusImmediate16" value="A9"/>
		<constant name="BP-BPPlusSIAddressPlusImmediate16" value="AA"/>
		<constant name="BP-BPPlusDIAddressPlusImmediate16" value="AB"/>
		<constant name="BP-SIAddressPlusImmediate16" value="AC"/>
		<constant name="BP-DIAddressPlusImmediate16" value="AD"/>
		<constant name="BP-BPAddressPlusImmediate16" value="AE"/>
		<constant name="BP-BXAddressPlusImmediate16" value="AF"/>
		<constant name="DH-BXPlusSIAddressPlusImmediate16" value="B0"/>
		<constant name="DH-BXPlusDIAddressPlusImmediate16" value="B1"/>
		<constant name="DH-BPPlusSIAddressPlusImmediate16" value="B2"/>
		<constant name="DH-BPPlusDIAddressPlusImmediate16" value="B3"/>
		<constant name="DH-SIAddressPlusImmediate16" value="B4"/>
		<constant name="DH-DIAddressPlusImmediate16" value="B5"/>
		<constant name="DH-BPAddressPlusImmediate16" value="B6"/>
		<constant name="DH-BXAddressPlusImmediate16" value="B7"/>
		<constant name="SI-BXPlusSIAddressPlusImmediate16" value="B0"/>
		<constant name="SI-BXPlusDIAddressPlusImmediate16" value="B1"/>
		<constant name="SI-BPPlusSIAddressPlusImmediate16" value="B2"/>
		<constant name="SI-BPPlusDIAddressPlusImmediate16" value="B3"/>
		<constant name="SI-SIAddressPlusImmediate16" value="B4"/>
		<constant name="SI-DIAddressPlusImmediate16" value="B5"/>
		<constant name="SI-BPAddressPlusImmediate16" value="B6"/>
		<constant name="SI-BXAddressPlusImmediate16" value="B7"/>
		<constant name="BH-BXPlusSIAddressPlusImmediate16" value="B8"/>
		<constant name="BH-BXPlusDIAddressPlusImmediate16" value="B9"/>
		<constant name="BH-BPPlusSIAddressPlusImmediate16" value="BA"/>
		<constant name="BH-BPPlusDIAddressPlusImmediate16" value="BB"/>
		<constant name="BH-SIAddressPlusImmediate16" value="BC"/>
		<constant name="BH-DIAddressPlusImmediate16" value="BD"/>
		<constant name="BH-BPAddressPlusImmediate16" value="BE"/>
		<constant name="BH-BXAddressPlusImmediate16" value="BF"/>
		<constant name="DI-BXPlusSIAddressPlusImmediate16" value="B8"/>
		<constant name="DI-BXPlusDIAddressPlusImmediate16" value="B9"/>
		<constant name="DI-BPPlusSIAddressPlusImmediate16" value="BA"/>
		<constant name="DI-BPPlusDIAddressPlusImmediate16" value="BB"/>
		<constant name="DI-SIAddressPlusImmediate16" value="BC"/>
		<constant name="DI-DIAddressPlusImmediate16" value="BD"/>
		<constant name="DI-BPAddressPlusImmediate16" value="BE"/>
		<constant name="DI-BXAddressPlusImmediate16" value="BF"/>
		<constant name="AL-ALRegister" value="C0"/>
		<constant name="AL-CLRegister" value="C1"/>
		<constant name="AL-DLRegister" value="C2"/>
		<constant name="AL-BLRegister" value="C3"/>
		<constant name="AL-AHRegister" value="C4"/>
		<constant name="AL-CHRegister" value="C5"/>
		<constant name="AL-DHRegister" value="C6"/>
		<constant name="AL-BHRegister" value="C7"/>
		<constant name="AX-AXRegister" value="C0"/>
		<constant name="AX-CXRegister" value="C1"/>
		<constant name="AX-DXRegister" value="C2"/>
		<constant name="AX-BXRegister" value="C3"/>
		<constant name="AX-SPRegister" value="C4"/>
		<constant name="AX-BPRegister" value="C5"/>
		<constant name="AX-SIRegister" value="C6"/>
		<constant name="AX-DIRegister" value="C7"/>
		<constant name="CL-ALRegister" value="C8"/>
		<constant name="CL-CLRegister" value="C9"/>
		<constant name="CL-DLRegister" value="CA"/>
		<constant name="CL-BLRegister" value="CB"/>
		<constant name="CL-AHRegister" value="CC"/>
		<constant name="CL-CHRegister" value="CD"/>
		<constant name="CL-DHRegister" value="CE"/>
		<constant name="CL-BHRegister" value="CF"/>
		<constant name="CX-AXRegister" value="C8"/>
		<constant name="CX-CXRegister" value="C9"/>
		<constant name="CX-DXRegister" value="CA"/>
		<constant name="CX-BXRegister" value="CB"/>
		<constant name="CX-SPRegister" value="CC"/>
		<constant name="CX-BPRegister" value="CD"/>
		<constant name="CX-SIRegister" value="CE"/>
		<constant name="CX-DIRegister" value="CF"/>
		<constant name="DL-ALRegister" value="D0"/>
		<constant name="DL-CLRegister" value="D1"/>
		<constant name="DL-DLRegister" value="D2"/>
		<constant name="DL-BLRegister" value="D3"/>
		<constant name="DL-AHRegister" value="D4"/>
		<constant name="DL-CHRegister" value="D5"/>
		<constant name="DL-DHRegister" value="D6"/>
		<constant name="DL-BHRegister" value="D7"/>
		<constant name="DX-AXRegister" value="D0"/>
		<constant name="DX-CXRegister" value="D1"/>
		<constant name="DX-DXRegister" value="D2"/>
		<constant name="DX-BXRegister" value="D3"/>
		<constant name="DX-SPRegister" value="D4"/>
		<constant name="DX-BPRegister" value="D5"/>
		<constant name="DX-SIRegister" value="D6"/>
		<constant name="DX-DIRegister" value="D7"/>
		<constant name="BL-ALRegister" value="D8"/>
		<constant name="BL-CLRegister" value="D9"/>
		<constant name="BL-DLRegister" value="DA"/>
		<constant name="BL-BLRegister" value="DB"/>
		<constant name="BL-AHRegister" value="DC"/>
		<constant name="BL-CHRegister" value="DD"/>
		<constant name="BL-DHRegister" value="DE"/>
		<constant name="BL-BHRegister" value="DF"/>
		<constant name="BX-AXRegister" value="D8"/>
		<constant name="BX-CXRegister" value="D9"/>
		<constant name="BX-DXRegister" value="DA"/>
		<constant name="BX-BXRegister" value="DB"/>
		<constant name="BX-SPRegister" value="DC"/>
		<constant name="BX-BPRegister" value="DD"/>
		<constant name="BX-SIRegister" value="DE"/>
		<constant name="BX-DIRegister" value="DF"/>
		<constant name="AH-ALRegister" value="E0"/>
		<constant name="AH-CLRegister" value="E1"/>
		<constant name="AH-DLRegister" value="E2"/>
		<constant name="AH-BLRegister" value="E3"/>
		<constant name="AH-AHRegister" value="E4"/>
		<constant name="AH-CHRegister" value="E5"/>
		<constant name="AH-DHRegister" value="E6"/>
		<constant name="AH-BHRegister" value="E7"/>
		<constant name="SP-AXRegister" value="E0"/>
		<constant name="SP-CXRegister" value="E1"/>
		<constant name="SP-DXRegister" value="E2"/>
		<constant name="SP-BXRegister" value="E3"/>
		<constant name="SP-SPRegister" value="E4"/>
		<constant name="SP-BPRegister" value="E5"/>
		<constant name="SP-SIRegister" value="E6"/>
		<constant name="SP-DIRegister" value="E7"/>
		<constant name="CH-ALRegister" value="E8"/>
		<constant name="CH-CLRegister" value="E9"/>
		<constant name="CH-DLRegister" value="EA"/>
		<constant name="CH-BLRegister" value="EB"/>
		<constant name="CH-AHRegister" value="EC"/>
		<constant name="CH-CHRegister" value="ED"/>
		<constant name="CH-DHRegister" value="EE"/>
		<constant name="CH-BHRegister" value="EF"/>
		<constant name="BP-AXRegister" value="E8"/>
		<constant name="BP-CXRegister" value="E9"/>
		<constant name="BP-DXRegister" value="EA"/>
		<constant name="BP-BXRegister" value="EB"/>
		<constant name="BP-SPRegister" value="EC"/>
		<constant name="BP-BPRegister" value="ED"/>
		<constant name="BP-SIRegister" value="EE"/>
		<constant name="BP-DIRegister" value="EF"/>
		<constant name="DH-ALRegister" value="F0"/>
		<constant name="DH-CLRegister" value="F1"/>
		<constant name="DH-DLRegister" value="F2"/>
		<constant name="DH-BLRegister" value="F3"/>
		<constant name="DH-AHRegister" value="F4"/>
		<constant name="DH-CHRegister" value="F5"/>
		<constant name="DH-DHRegister" value="F6"/>
		<constant name="DH-BHRegister" value="F7"/>
		<constant name="SI-AXRegister" value="F0"/>
		<constant name="SI-CXRegister" value="F1"/>
		<constant name="SI-DXRegister" value="F2"/>
		<constant name="SI-BXRegister" value="F3"/>
		<constant name="SI-SPRegister" value="F4"/>
		<constant name="SI-BPRegister" value="F5"/>
		<constant name="SI-SIRegister" value="F6"/>
		<constant name="SI-DIRegister" value="F7"/>
		<constant name="BH-ALRegister" value="F8"/>
		<constant name="BH-CLRegister" value="F9"/>
		<constant name="BH-DLRegister" value="FA"/>
		<constant name="BH-BLRegister" value="FB"/>
		<constant name="BH-AHRegister" value="FC"/>
		<constant name="BH-CHRegister" value="FD"/>
		<constant name="BH-DHRegister" value="FE"/>
		<constant name="BH-BHRegister" value="FF"/>
		<constant name="DI-AXRegister" value="F8"/>
		<constant name="DI-CXRegister" value="F9"/>
		<constant name="DI-DXRegister" value="FA"/>
		<constant name="DI-BXRegister" value="FB"/>
		<constant name="DI-SPRegister" value="FC"/>
		<constant name="DI-BPRegister" value="FD"/>
		<constant name="DI-SIRegister" value="FE"/>
		<constant name="DI-DIRegister" value="FF"/>
	</constants>
</platform>